{
    "utilisateurs": [
        {
            "id": 1,
            "prenom": "Jacques",
            "nom": "Adit",
            "email": "jacques.adit@mail.fr",
            "address": {
                "street": "2 avenue du chocolat",
                "zipcode": "12345",
                "city": "QuelquePart"
            }
        },
        {
            "id": 2,
            "prenom": "Thierry",
            "nom": "Napadi",
            "email": "thierry.napadi@mail.fr",
            "address": {
                "street": "3 avenue du chocolat",
                "zipcode": "12345",
                "city": "QuelquePart"
            }
        },
        {
            "id": 3,
            "prenom": "marc",
            "nom": "Asin",
            "email": "marc.asin@mail.fr",
            "address": {
                "street": "16 rue de la date",
                "zipcode": "12345",
                "city": "NullePart"
            }
        }
    ]
}